setup.py
ipy_progressbar/__init__.py
ipy_progressbar/base.py
ipy_progressbar/ipynb_bar.py
ipy_progressbar/terminal_bar.py
ipy_progressbar.egg-info/PKG-INFO
ipy_progressbar.egg-info/SOURCES.txt
ipy_progressbar.egg-info/dependency_links.txt
ipy_progressbar.egg-info/not-zip-safe
ipy_progressbar.egg-info/top_level.txt