Metadata-Version: 1.1
Name: ipy-progressbar
Version: 1.0.3
Summary: Progressbar for both IPython Notebooks (HTML, CSS, JS) and plain terminals.
Home-page: https://hg.plav.in/my_projects/python/ipy-progressbar
Author: Alexander Plavin
Author-email: alexander@plav.in
License: MIT
Keywords: progress progressbar terminal console ipython notebook
Platform: UNKNOWN
Classifier: Development Status :: 5 - Production/Stable
Classifier: Environment :: Console
Classifier: Environment :: Web Environment
Classifier: Framework :: IPython
Classifier: Intended Audience :: Developers
Classifier: License :: OSI Approved :: MIT License
Classifier: Natural Language :: English
Classifier: Operating System :: OS Independent
Classifier: Programming Language :: Python :: 2.7
Classifier: Topic :: Software Development :: Libraries :: Python Modules
Classifier: Topic :: Software Development :: User Interfaces
Classifier: Topic :: Terminals
